[
  {
    "id": 1,
    "priority": 1,
    "action": {
      "type": "block"
    },
    "condition": {
      "urlFilter": "analytics.js",
      "resourceTypes": ["script"]
    }
  },
  {
    "id": 2,
    "priority": 1,
    "action": {
      "type": "block"
    },
    "condition": {
      "urlFilter": "gtag.js",
      "resourceTypes": ["script"]
    }
  },
  {
    "id": 3,
    "priority": 1,
    "action": {
      "type": "block"
    },
    "condition": {
      "urlFilter": "ga.js",
      "resourceTypes": ["script"]
    }
  }
]
